setup.py
kcwredis/__init__.py
kcwredis/redisclass.py
kcwredis.egg-info/PKG-INFO
kcwredis.egg-info/SOURCES.txt
kcwredis.egg-info/dependency_links.txt
kcwredis.egg-info/requires.txt
kcwredis.egg-info/top_level.txt